Metadata-Version: 2.1
Name: ScrapyAppSearch
Version: 0.1.0
Summary: Scrapy pipeline which allow you to store multiple scrapy items in AppSearch.
Home-page: https://github.com/llermaly/scrapy-appsearch.git
Author: Gustavo Llermaly, Jay Zeng, Michael Malocha, Julien Duponchelle
Author-email: gllermaly@gmail.com, jayzeng@jay-zeng.com, michael@knockrentals.com, julien@duponchelle.info
License: Apache License, Version 2.0
Download-URL: https://github.com/llermaly/scrapy-appsearch/archive/v0.1.0.tar.gz
Keywords: scrapy appsearch
Platform: Any
Classifier: Development Status :: 4 - Beta
Classifier: Environment :: No Input/Output (Daemon)
Classifier: License :: OSI Approved :: Apache Software License
Classifier: Operating System :: OS Independent
Classifier: Programming Language :: Python
